README.md
setup.py
configclasses/__init__.py
configclasses/configclass.py
configclasses/conversions.py
configclasses/enums.py
configclasses/sources.py
configclasses.egg-info/PKG-INFO
configclasses.egg-info/SOURCES.txt
configclasses.egg-info/dependency_links.txt
configclasses.egg-info/requires.txt
configclasses.egg-info/top_level.txt