Metadata-Version: 2.1
Name: configclasses
Version: 0.4.5
Summary: Strongly typed configuration classes made simple and effective.
Home-page: http://github.com/jeffbelgum/configclasses
Author: Jeff Belgum
Author-email: jeffbelgum@gmail.com
License: MIT/APACHE-2.0
Keywords: configuration settings config environment typed dataclasses
Platform: UNKNOWN
Classifier: Development Status :: 4 - Beta
Classifier: Intended Audience :: Developers
Classifier: Topic :: Software Development :: Libraries
Classifier: Topic :: Software Development :: Libraries :: Python Modules
Classifier: License :: OSI Approved :: MIT License
Classifier: License :: OSI Approved :: Apache Software License
Classifier: Programming Language :: Python :: 3.6
Classifier: Programming Language :: Python :: 3.7
Requires-Python: >=3.6
Provides-Extra: test
Provides-Extra: dev
